orgui/__init__.py
orgui/_version.py
orgui/main.py
orgui/app/ArrayTableDialog.py
orgui/app/QHKLDialog.py
orgui/app/QReflectionSelector.py
orgui/app/QScanSelector.py
orgui/app/QUBCalculator.py
orgui/app/ROIutils.py
orgui/app/__init__.py
orgui/app/_roi_sum_accel.py
orgui/app/bgroi.py
orgui/app/database.py
orgui/app/imagePeakFinder.py
orgui/app/orGUI.py
orgui/app/peak1Dintegr.py
orgui/app/qutils.py
orgui/backend/__init__.py
orgui/backend/backends.py
orgui/backend/interlacedScanLoader.py
orgui/backend/scans.py
orgui/backend/udefaults.py
orgui/backend/universalScanLoader.py
orgui/backend/beamline/ID31DiffractLinTilt.py
orgui/backend/beamline/P212_tools.py
orgui/backend/beamline/__init__.py
orgui/backend/beamline/fio_reader.py
orgui/backend/beamline/id31_tools.py
orgui/datautils/__init__.py
orgui/datautils/util.py
orgui/datautils/xrayutils/CTRcalc.py
orgui/datautils/xrayutils/CTRfilm.py
orgui/datautils/xrayutils/CTRopt.py
orgui/datautils/xrayutils/CTRplotutil.py
orgui/datautils/xrayutils/CTRuc.py
orgui/datautils/xrayutils/CTRutil.py
orgui/datautils/xrayutils/DetectorCalibration.py
orgui/datautils/xrayutils/HKLVlieg.py
orgui/datautils/xrayutils/ReciprocalNavigation.py
orgui/datautils/xrayutils/_CTRcalc_accel.py
orgui/datautils/xrayutils/__init__.py
orgui/datautils/xrayutils/element_data.py
orgui/datautils/xrayutils/test/__init__.py
orgui/datautils/xrayutils/test/test_CTRcalc.py
orgui/datautils/xrayutils/test/test_DetectorCalibration.py
orgui/datautils/xrayutils/test/test_HKLcalc.py
orgui/datautils/xrayutils/unitcells/Fe3O4(100).bul
orgui/datautils/xrayutils/unitcells/Pt100.bul
orgui/datautils/xrayutils/unitcells/Pt100_small.bul
orgui/datautils/xrayutils/unitcells/Pt110.bul
orgui/datautils/xrayutils/unitcells/Pt111.bul
orgui/datautils/xrayutils/unitcells/Pt310.bul
orgui/datautils/xrayutils/unitcells/Pt3O4(100).bul
orgui/datautils/xrayutils/unitcells/PtO(001).bul
orgui/datautils/xrayutils/unitcells/PtO(010).bul
orgui/datautils/xrayutils/unitcells/PtO(100).bul
orgui-1.4.0.dist-info/licenses/LICENSE
orgui-1.4.0.dist-info/METADATA
orgui-1.4.0.dist-info/WHEEL
orgui-1.4.0.dist-info/entry_points.txt
orgui-1.4.0.dist-info/top_level.txt
orgui-1.4.0.dist-info/RECORD
