Metadata-Version: 2.4
Name: orGUI
Version: 1.4.0
Summary: orGUI: Orientation and Integration with 2D detectors
Author-email: Timo Fuchs <tfuchs@cornell.edu>
License-Expression: MIT
Classifier: Development Status :: 5 - Production/Stable
Classifier: Environment :: Win32 (MS Windows)
Classifier: Environment :: X11 Applications :: Qt
Classifier: Intended Audience :: End Users/Desktop
Classifier: Intended Audience :: Developers
Classifier: Intended Audience :: Science/Research
Classifier: Operating System :: MacOS :: MacOS X
Classifier: Operating System :: Microsoft :: Windows
Classifier: Operating System :: POSIX
Classifier: Programming Language :: Python
Classifier: Programming Language :: Python :: 3
Classifier: Programming Language :: Python :: Implementation :: CPython
Classifier: Topic :: Scientific/Engineering :: Chemistry
Classifier: Topic :: Scientific/Engineering :: Physics
Classifier: Topic :: Scientific/Engineering :: Visualization
Classifier: Topic :: Software Development :: Libraries :: Python Modules
Requires-Python: >=3.8
License-File: LICENSE
Requires-Dist: numpy>=1.12
Requires-Dist: scipy>=1.0
Requires-Dist: matplotlib>=1.2
Requires-Dist: fabio>=0.7
Requires-Dist: silx>=1.1
Requires-Dist: pyFAI>=0.19
Requires-Dist: pymca>=5.3
Requires-Dist: xraydb>=4.0
Requires-Dist: pytz>=2022
Provides-Extra: console
Requires-Dist: qtconsole; extra == "console"
Provides-Extra: speedup
Requires-Dist: numba; extra == "speedup"
Provides-Extra: extendedfilesupport
Requires-Dist: ase; extra == "extendedfilesupport"
Requires-Dist: hdf5plugin; extra == "extendedfilesupport"
Provides-Extra: full
Requires-Dist: qtconsole; extra == "full"
Requires-Dist: ase; extra == "full"
Requires-Dist: numba; extra == "full"
Requires-Dist: PyOpenGL; extra == "full"
Requires-Dist: hdf5plugin; extra == "full"
Dynamic: license-file
